<!DOCTYPE USUARIOS_P2P SYSTEM "USUARIOS.XSL">
<USUARIOS_P2P>
	<USUARIO>
		<NICK>Luis</NICK>
		<NOMBRE_COMPLETO>Luis Gasco</NOMBRE_COMPLETO>
		<PUERTO_P2P>3456</PUERTO_P2P>
		<DIRECTORIO_EXPORTADO>E:\COMPARTIDO-REDESII\Luis</DIRECTORIO_EXPORTADO>
		<CORREO_ELECTRONICO>luisgp@ya.com</CORREO_ELECTRONICO>
		<CLAVE>0123h567890o2345678901234l678901234567890123456789012aRESTO</CLAVE>
	</USUARIO>
	<USUARIO>
		<NICK>admin</NICK>
		<NOMBRE_COMPLETO>Luis Gasco</NOMBRE_COMPLETO>
		<PUERTO_P2P>1234</PUERTO_P2P>
		<DIRECTORIO_EXPORTADO>E:\COMPARTIDO-REDESII\admin</DIRECTORIO_EXPORTADO>
		<CORREO_ELECTRONICO>admin@redesii</CORREO_ELECTRONICO>
		<CLAVE>01234a6789012d456789012345678m012345...__</CLAVE>
	</USUARIO>
</USUARIOS_P2P>
